hyperfit/__init__.py
hyperfit/data.py
hyperfit/linfit.py
hyperfit/data/Example.txt
hyperfit/data/FP6dFGS.txt
hyperfit/data/GAMAsmVsize.txt
hyperfit/data/Hogg.txt
hyperfit/data/MJB.txt
hyperfit/data/TFR.txt
hyperfit-0.1.7.dist-info/LICENSE.txt
hyperfit-0.1.7.dist-info/METADATA
hyperfit-0.1.7.dist-info/WHEEL
hyperfit-0.1.7.dist-info/top_level.txt
hyperfit-0.1.7.dist-info/RECORD
