Metadata-Version: 2.1
Name: hyperfit
Version: 0.1.7
Summary: Properly fit data with x and y errors
Home-page: https://github.com/CullanHowlett/HyperFit
Author: Cullan Howlett
Author-email: cullan.howlett@gmail.com
Project-URL: Bug Reports, https://github.com/CullanHowlett/HyperFit/issues
Classifier: Development Status :: 3 - Alpha
Classifier: Intended Audience :: Science/Research
Classifier: Topic :: Scientific/Engineering
Classifier: License :: OSI Approved :: MIT License
Classifier: Operating System :: OS Independent
Classifier: Programming Language :: Python :: 3.9
Requires-Python: >=3.7, <4
License-File: LICENSE.txt
Requires-Dist: numpy (>=1.20.0)
Requires-Dist: scipy (>=1.6.0)
Requires-Dist: zeus-mcmc (>=2.3.0)
Requires-Dist: pandas (>=1.2.0)
Requires-Dist: emcee (>=3.0.0)
Requires-Dist: snowline (>=0.5.0)
